llama_index/llms/databricks/__init__.py
llama_index/llms/databricks/base.py
llama_index_llms_databricks-0.4.1.dist-info/METADATA
llama_index_llms_databricks-0.4.1.dist-info/WHEEL
llama_index_llms_databricks-0.4.1.dist-info/licenses/LICENSE
llama_index_llms_databricks-0.4.1.dist-info/RECORD
